timeback_core/__init__.py
timeback_core/broadcast.py
timeback_core/client.py
timeback_core/constants.py
timeback_core/manager.py
timeback_core/provider.py
timeback_core/py.typed
timeback_core/types.py
timeback_core-0.1.4.dist-info/METADATA
timeback_core-0.1.4.dist-info/WHEEL
timeback_core-0.1.4.dist-info/RECORD
