Metadata-Version: 2.4
Name: timeback-core
Version: 0.1.4
Summary: Unified Timeback client for all education APIs (OneRoster, Caliper, Edubridge)
Project-URL: Homepage, https://developer.timeback.com
Project-URL: Documentation, https://docs.timeback.com
Project-URL: Repository, https://github.com/superbuilders/timeback-dev-python
Author-email: Timeback <dev@timeback.dev>
License-Expression: MIT
Classifier: Development Status :: 3 - Alpha
Classifier: Intended Audience :: Developers
Classifier: License :: OSI Approved :: MIT License
Classifier: Programming Language :: Python :: 3
Classifier: Programming Language :: Python :: 3.12
Classifier: Programming Language :: Python :: 3.13
Classifier: Typing :: Typed
Requires-Python: >=3.12
Requires-Dist: timeback-caliper>=0.1.0
Requires-Dist: timeback-common>=0.1.0
Requires-Dist: timeback-edubridge>=0.1.0
Requires-Dist: timeback-oneroster>=0.1.0
